cognitivecluster/__init__.py
cognitivecluster/clusters.py
cognitivecluster-0.2.1.dist-info/LICENSE.md
cognitivecluster-0.2.1.dist-info/WHEEL
cognitivecluster-0.2.1.dist-info/METADATA
cognitivecluster-0.2.1.dist-info/RECORD
